sp_lh3_constant_contact/__init__.py
sp_lh3_constant_contact-0.1.6.dist-info/METADATA
sp_lh3_constant_contact-0.1.6.dist-info/WHEEL
sp_lh3_constant_contact-0.1.6.dist-info/RECORD
